frogmouth/__init__.py
frogmouth/__main__.py
frogmouth/app/__init__.py
frogmouth/app/app.py
frogmouth/data/__init__.py
frogmouth/data/bookmarks.py
frogmouth/data/config.py
frogmouth/data/data_directory.py
frogmouth/data/history.py
frogmouth/dialogs/__init__.py
frogmouth/dialogs/error.py
frogmouth/dialogs/help_dialog.py
frogmouth/dialogs/information.py
frogmouth/dialogs/input_dialog.py
frogmouth/dialogs/text_dialog.py
frogmouth/dialogs/yes_no_dialog.py
frogmouth/screens/__init__.py
frogmouth/screens/main.py
frogmouth/utility/__init__.py
frogmouth/utility/advertising.py
frogmouth/utility/forge.py
frogmouth/utility/type_tests.py
frogmouth/widgets/__init__.py
frogmouth/widgets/navigation.py
frogmouth/widgets/navigation_panes/__init__.py
frogmouth/widgets/navigation_panes/bookmarks.py
frogmouth/widgets/navigation_panes/history.py
frogmouth/widgets/navigation_panes/local_files.py
frogmouth/widgets/navigation_panes/navigation_pane.py
frogmouth/widgets/navigation_panes/table_of_contents.py
frogmouth/widgets/omnibox.py
frogmouth/widgets/viewer.py
frogmouth_ng-0.9.2.dist-info/METADATA
frogmouth_ng-0.9.2.dist-info/WHEEL
frogmouth_ng-0.9.2.dist-info/entry_points.txt
frogmouth_ng-0.9.2.dist-info/licenses/LICENSE
frogmouth_ng-0.9.2.dist-info/RECORD
