Metadata-Version: 2.4
Name: frogmouth-ng
Version: 0.9.2
Summary: A Markdown document viewer for the terminal
License-Expression: MIT
License-File: LICENSE
Author: Dave Pearson
Author-email: dave@textualize.io
Maintainer: Viriathus1
Maintainer-email: viriathus1_dev@proton.me
Requires-Python: >=3.10
Classifier: Development Status :: 4 - Beta
Classifier: Environment :: Console
Classifier: Intended Audience :: Developers
Classifier: Intended Audience :: End Users/Desktop
Classifier: Intended Audience :: Information Technology
Classifier: Intended Audience :: Other Audience
Classifier: Operating System :: MacOS
Classifier: Operating System :: Microsoft :: Windows :: Windows 10
Classifier: Operating System :: Microsoft :: Windows :: Windows 11
Classifier: Operating System :: POSIX :: Linux
Classifier: Programming Language :: Python :: 3.10
Classifier: Programming Language :: Python :: 3.11
Classifier: Programming Language :: Python :: 3.12
Classifier: Programming Language :: Python :: 3.13
Classifier: Programming Language :: Python :: 3.14
Classifier: Topic :: Software Development :: Documentation
Classifier: Topic :: Text Processing :: Markup :: Markdown
Requires-Dist: httpx (>=0.28.1,<0.29.0)
Requires-Dist: textual (==0.53.1)
Requires-Dist: typing-extensions (>=4.12.0,<5.0.0)
Requires-Dist: xdg-base-dirs (>=6.0.2,<7.0.0)
Project-URL: Homepage, https://github.com/Viriathus1/frogmouth-ng
